{"name": "rec_0000/1682720371014_final.png", "videoName": "rec_0000", "resolution": {"width": 1920, "height": 1080}, "extrinsics": {"location": [-318.43475341796875, -21.777320861816406, 85.4583511352539], "rotation": [-0.5807804394697718, 0.00846542188610255, -1.9234029830210773]}, "attributes": {"scene": "undefined", "timeofday": "daytime", "weather": "CLEAR"}, "intrinsics": {"focal": [960.0, 960.0], "center": [960, 540], "fov": 59.0, "nearClip": 0.15, "cali": [[960.0, 0, 960, 0], [0, 960.0, 540, 0], [0, 0, 0, 1]]}, "frameIndex": 19, "timestamp": 1682720371014, "labels": [{"id": 28418, "category": "Car", "manualShape": false, "manualAttributes": false, "attributes": {"occluded": 0, "truncated": 0, "ignore": false}, "box2d": {"x1": 1296, "y1": 416, "x2": 1354, "y2": 438, "confidence": 1.0}, "box3d": {"alpha": 2.55541, "orientation": 2.91993, "location": [31.0224, -9.10635, 81.3025], "dimension": [1.4331, 1.92351, 5.14386]}}, {"id": 39170, "category": "Car", "manualShape": false, "manualAttributes": false, "attributes": {"occluded": 0, "truncated": 0, "ignore": false}, "box2d": {"x1": 930, "y1": 125, "x2": 941, "y2": 141, "confidence": 1.0}, "box3d": {"alpha": 1.58133, "orientation": 1.55624, "location": [-4.09556, -68.5758, 163.207], "dimension": [1.95105, 2.10791, 5.10333]}}, {"id": 40706, "category": "Car", "manualShape": false, "manualAttributes": false, "attributes": {"occluded": 0, "truncated": 0, "ignore": false}, "box2d": {"x1": 955, "y1": 12, "x2": 959, "y2": 16, "confidence": 1.0}, "box3d": {"alpha": -1.54339, "orientation": -1.5462, "location": [-0.973106, -190.082, 346.801], "dimension": [1.77739, 2.13761, 4.78141]}}, {"id": 50434, "category": "Car", "manualShape": false, "manualAttributes": false, "attributes": {"occluded": 0, "truncated": 0, "ignore": false}, "box2d": {"x1": 1385, "y1": 404, "x2": 1439, "y2": 433, "confidence": 1.0}, "box3d": {"alpha": 2.35315, "orientation": 2.79279, "location": [39.1926, -9.80887, 83.3279], "dimension": [1.87449, 2.08947, 4.82045]}}, {"id": 51202, "category": "Car", "manualShape": false, "manualAttributes": false, "attributes": {"occluded": 0, "truncated": 0, "ignore": false}, "box2d": {"x1": 1436, "y1": 398, "x2": 1486, "y2": 421, "confidence": 1.0}, "box3d": {"alpha": 2.30148, "orientation": 2.78322, "location": [45.1398, -11.2824, 86.3373], "dimension": [1.3941, 2.00371, 5.0106]}}, {"id": 58114, "category": "Car", "manualShape": false, "manualAttributes": false, "attributes": {"occluded": 0, "truncated": 0, "ignore": false}, "box2d": {"x1": 557, "y1": 468, "x2": 623, "y2": 492, "confidence": 1.0}, "box3d": {"alpha": 0.216504, "orientation": -0.151592, "location": [-28.4215, -4.14698, 73.6931], "dimension": [1.49636, 2.00041, 4.91436]}}, {"id": 63746, "category": "Car", "manualShape": false, "manualAttributes": false, "attributes": {"occluded": 0, "truncated": 0, "ignore": false}, "box2d": {"x1": 654, "y1": 458, "x2": 714, "y2": 489, "confidence": 1.0}, "box3d": {"alpha": 0.174965, "orientation": -0.102845, "location": [-21.2304, -4.4945, 74.4442], "dimension": [1.87449, 2.08947, 4.82045]}}, {"id": 71682, "category": "Car", "manualShape": false, "manualAttributes": false, "attributes": {"occluded": 0, "truncated": 0, "ignore": false}, "box2d": {"x1": 931, "y1": 29, "x2": 936, "y2": 34, "confidence": 1.0}, "box3d": {"alpha": 1.60343, "orientation": 1.57646, "location": [-7.53314, -147.932, 279.275], "dimension": [1.68732, 1.92351, 4.95318]}}, {"id": 71938, "category": "Car", "manualShape": false, "manualAttributes": false, "attributes": {"occluded": 0, "truncated": 0, "ignore": false}, "box2d": {"x1": 926, "y1": 33, "x2": 932, "y2": 38, "confidence": 1.0}, "box3d": {"alpha": 1.61579, "orientation": 1.58361, "location": [-8.59378, -140.3, 266.967], "dimension": [1.49636, 2.00041, 4.91436]}}, {"id": 80898, "category": "Car", "manualShape": false, "manualAttributes": false, "attributes": {"occluded": 0, "truncated": 0, "ignore": false}, "box2d": {"x1": 936, "y1": 14, "x2": 940, "y2": 18, "confidence": 1.0}, "box3d": {"alpha": 1.59519, "orientation": 1.57291, "location": [-7.57462, -185.729, 339.922], "dimension": [1.3941, 2.00371, 5.0106]}}, {"id": 82946, "category": "Car", "manualShape": false, "manualAttributes": false, "attributes": {"occluded": 0, "truncated": 0, "ignore": false}, "box2d": {"x1": 758, "y1": 880, "x2": 816, "y2": 997, "confidence": 1.0}, "box3d": {"alpha": 1.72155, "orientation": 1.54518, "location": [-7.39833, 17.8024, 41.512], "dimension": [1.95105, 2.10791, 5.10333]}}, {"id": 89858, "category": "Car", "manualShape": false, "manualAttributes": false, "attributes": {"occluded": 0, "truncated": 0, "ignore": false}, "box2d": {"x1": 916, "y1": 676, "x2": 950, "y2": 754, "confidence": 1.0}, "box3d": {"alpha": 1.5517, "orientation": 1.52378, "location": [-1.46378, 9.98362, 52.4108], "dimension": [1.46187, 2.18793, 5.21102]}}, {"id": 98306, "category": "Car", "manualShape": false, "manualAttributes": false, "attributes": {"occluded": 0, "truncated": 0, "ignore": false}, "box2d": {"x1": 550, "y1": 540, "x2": 624, "y2": 567, "confidence": 1.0}, "box3d": {"alpha": 0.279707, "orientation": -0.0918196, "location": [-25.4821, 1.40745, 65.4024], "dimension": [1.49636, 2.00041, 4.91436]}}, {"id": 129026, "category": "Car", "manualShape": false, "manualAttributes": false, "attributes": {"occluded": 0, "truncated": 0, "ignore": false}, "box2d": {"x1": 921, "y1": 15, "x2": 926, "y2": 19, "confidence": 1.0}, "box3d": {"alpha": 1.62207, "orientation": 1.5842, "location": [-12.7323, -183.155, 336.072], "dimension": [1.4331, 1.92351, 5.14386]}}, {"id": 131074, "category": "Car", "manualShape": false, "manualAttributes": false, "attributes": {"occluded": 0, "truncated": 0, "ignore": false}, "box2d": {"x1": 950, "y1": 1, "x2": 955, "y2": 6, "confidence": 1.0}, "box3d": {"alpha": 1.49991, "orientation": 1.49241, "location": [-2.91515, -217.28, 388.677], "dimension": [1.87449, 2.08947, 4.82045]}}]}