{"name": "rec_0000/1682720393154_final.png", "videoName": "rec_0000", "resolution": {"width": 1920, "height": 1080}, "extrinsics": {"location": [-149.7039794921875, -83.84028625488281, 76.71485137939453], "rotation": [-0.523177763119471, -0.02172426013615761, -1.9089321646059139]}, "attributes": {"scene": "undefined", "timeofday": "daytime", "weather": "CLEAR"}, "intrinsics": {"focal": [960.0, 960.0], "center": [960, 540], "fov": 59.0, "nearClip": 0.15, "cali": [[960.0, 0, 960, 0], [0, 960.0, 540, 0], [0, 0, 0, 1]]}, "frameIndex": 85, "timestamp": 1682720393154, "labels": [{"id": 33794, "category": "Car", "manualShape": false, "manualAttributes": false, "attributes": {"occluded": 0, "truncated": 0, "ignore": false}, "box2d": {"x1": 982, "y1": 114, "x2": 990, "y2": 122, "confidence": 1.0}, "box3d": {"alpha": -1.557, "orientation": -1.52912, "location": [5.1929, -81.5424, 186.204], "dimension": [1.4331, 1.92351, 5.14386]}}, {"id": 50946, "category": "Car", "manualShape": false, "manualAttributes": false, "attributes": {"occluded": 0, "truncated": 0, "ignore": false}, "box2d": {"x1": 869, "y1": 200, "x2": 890, "y2": 217, "confidence": 1.0}, "box3d": {"alpha": 1.67636, "orientation": 1.59352, "location": [-7.9649, -32.6976, 95.925], "dimension": [1.68732, 1.92351, 4.95318]}}, {"id": 99842, "category": "Car", "manualShape": false, "manualAttributes": false, "attributes": {"occluded": 0, "truncated": 0, "ignore": false}, "box2d": {"x1": 876, "y1": 186, "x2": 896, "y2": 203, "confidence": 1.0}, "box3d": {"alpha": 1.69649, "orientation": 1.61988, "location": [-7.84984, -36.3305, 102.266], "dimension": [1.49636, 2.00041, 4.91436]}}, {"id": 107778, "category": "Car", "manualShape": false, "manualAttributes": false, "attributes": {"occluded": 0, "truncated": 0, "ignore": false}, "box2d": {"x1": 984, "y1": 109, "x2": 994, "y2": 118, "confidence": 1.0}, "box3d": {"alpha": -1.56829, "orientation": -1.53802, "location": [5.83645, -85.0757, 192.702], "dimension": [1.87449, 2.08947, 4.82045]}}, {"id": 125698, "category": "Car", "manualShape": false, "manualAttributes": false, "attributes": {"occluded": 0, "truncated": 0, "ignore": false}, "box2d": {"x1": 958, "y1": 109, "x2": 966, "y2": 116, "confidence": 1.0}, "box3d": {"alpha": -1.52522, "orientation": -1.52258, "location": [0.520248, -87.4592, 196.942], "dimension": [1.4331, 1.92351, 5.14386]}}, {"id": 150786, "category": "Car", "manualShape": false, "manualAttributes": false, "attributes": {"occluded": 0, "truncated": 0, "ignore": false}, "box2d": {"x1": 820, "y1": 200, "x2": 843, "y2": 219, "confidence": 1.0}, "box3d": {"alpha": 1.73732, "orientation": 1.60407, "location": [-12.7797, -32.3237, 95.3395], "dimension": [1.49636, 2.00041, 4.91436]}}, {"id": 157442, "category": "Car", "manualShape": false, "manualAttributes": false, "attributes": {"occluded": 0, "truncated": 0, "ignore": false}, "box2d": {"x1": 1006, "y1": 185, "x2": 1029, "y2": 199, "confidence": 1.0}, "box3d": {"alpha": -1.84634, "orientation": -1.78639, "location": [6.37554, -38.025, 106.217], "dimension": [1.49636, 2.00041, 4.91436]}}, {"id": 169474, "category": "Car", "manualShape": false, "manualAttributes": false, "attributes": {"occluded": 0, "truncated": 0, "ignore": false}, "box2d": {"x1": 984, "y1": 188, "x2": 1002, "y2": 202, "confidence": 1.0}, "box3d": {"alpha": -1.63314, "orientation": -1.59794, "location": [3.67128, -37.0419, 104.241], "dimension": [1.68732, 1.92351, 4.95318]}}, {"id": 179970, "category": "Car", "manualShape": false, "manualAttributes": false, "attributes": {"occluded": 0, "truncated": 0, "ignore": false}, "box2d": {"x1": 1247, "y1": 231, "x2": 1298, "y2": 256, "confidence": 1.0}, "box3d": {"alpha": 2.65099, "orientation": 2.96479, "location": [28.6363, -26.5535, 88.2418], "dimension": [1.87449, 2.08947, 4.82045]}}, {"id": 189954, "category": "Car", "manualShape": false, "manualAttributes": false, "attributes": {"occluded": 0, "truncated": 0, "ignore": false}, "box2d": {"x1": 893, "y1": 172, "x2": 909, "y2": 186, "confidence": 1.0}, "box3d": {"alpha": 1.6773, "orientation": 1.61587, "location": [-7.04104, -42.6672, 114.484], "dimension": [1.33549, 1.98119, 5.59612]}}, {"id": 190466, "category": "Car", "manualShape": false, "manualAttributes": false, "attributes": {"occluded": 0, "truncated": 0, "ignore": false}, "box2d": {"x1": 931, "y1": 191, "x2": 949, "y2": 207, "confidence": 1.0}, "box3d": {"alpha": 1.60141, "orientation": 1.5812, "location": [-2.04444, -35.5891, 101.189], "dimension": [1.33549, 1.98119, 5.59612]}}, {"id": 195842, "category": "Car", "manualShape": false, "manualAttributes": false, "attributes": {"occluded": 0, "truncated": 0, "ignore": false}, "box2d": {"x1": 913, "y1": 161, "x2": 937, "y2": 180, "confidence": 1.0}, "box3d": {"alpha": 1.25541, "orientation": 1.2189, "location": [-4.35309, -45.0777, 119.155], "dimension": [1.95105, 2.10791, 5.10333]}}, {"id": 196354, "category": "Car", "manualShape": false, "manualAttributes": false, "attributes": {"occluded": 0, "truncated": 0, "ignore": false}, "box2d": {"x1": 1339, "y1": 250, "x2": 1388, "y2": 269, "confidence": 1.0}, "box3d": {"alpha": 2.5442, "orientation": 2.94193, "location": [37.5541, -25.6309, 89.3897], "dimension": [1.3941, 2.00371, 5.0106]}}, {"id": 199170, "category": "Car", "manualShape": false, "manualAttributes": false, "attributes": {"occluded": 0, "truncated": 0, "ignore": false}, "box2d": {"x1": 882, "y1": 132, "x2": 895, "y2": 142, "confidence": 1.0}, "box3d": {"alpha": 1.71751, "orientation": 1.64331, "location": [-11.4007, -63.9348, 153.348], "dimension": [1.4331, 1.92351, 5.14386]}}, {"id": 199682, "category": "Car", "manualShape": false, "manualAttributes": false, "attributes": {"occluded": 0, "truncated": 0, "ignore": false}, "box2d": {"x1": 902, "y1": 153, "x2": 916, "y2": 165, "confidence": 1.0}, "box3d": {"alpha": 1.67428, "orientation": 1.62154, "location": [-6.86286, -51.1099, 129.995], "dimension": [1.49636, 2.00041, 4.91436]}}, {"id": 207874, "category": "Car", "manualShape": false, "manualAttributes": false, "attributes": {"occluded": 0, "truncated": 0, "ignore": false}, "box2d": {"x1": 864, "y1": 151, "x2": 879, "y2": 163, "confidence": 1.0}, "box3d": {"alpha": 1.70055, "orientation": 1.60858, "location": [-12.1577, -52.1326, 131.82], "dimension": [1.49636, 2.00041, 4.91436]}}, {"id": 209154, "category": "Car", "manualShape": false, "manualAttributes": false, "attributes": {"occluded": 0, "truncated": 0, "ignore": false}, "box2d": {"x1": 909, "y1": 136, "x2": 923, "y2": 152, "confidence": 1.0}, "box3d": {"alpha": 1.65064, "orientation": 1.60553, "location": [-6.46697, -58.3652, 143.26], "dimension": [1.95105, 2.10791, 5.10333]}}, {"id": 211970, "category": "Car", "manualShape": false, "manualAttributes": false, "attributes": {"occluded": 0, "truncated": 0, "ignore": false}, "box2d": {"x1": 920, "y1": 132, "x2": 931, "y2": 140, "confidence": 1.0}, "box3d": {"alpha": 1.63723, "orientation": 1.60218, "location": [-5.48099, -65.4995, 156.321], "dimension": [1.68732, 1.92351, 4.95318]}}, {"id": 217858, "category": "Car", "manualShape": false, "manualAttributes": false, "attributes": {"occluded": 0, "truncated": 0, "ignore": false}, "box2d": {"x1": 911, "y1": 102, "x2": 924, "y2": 112, "confidence": 1.0}, "box3d": {"alpha": 1.8845, "orientation": 1.84062, "location": [-8.85545, -90.366, 201.674], "dimension": [1.95105, 2.10791, 5.10333]}}, {"id": 224258, "category": "Car", "manualShape": false, "manualAttributes": false, "attributes": {"occluded": 0, "truncated": 0, "ignore": false}, "box2d": {"x1": 926, "y1": 94, "x2": 936, "y2": 100, "confidence": 1.0}, "box3d": {"alpha": 1.75911, "orientation": 1.72922, "location": [-6.64453, -102.285, 222.229], "dimension": [1.49636, 2.00041, 4.91436]}}, {"id": 226818, "category": "Car", "manualShape": false, "manualAttributes": false, "attributes": {"occluded": 0, "truncated": 0, "ignore": false}, "box2d": {"x1": 922, "y1": 87, "x2": 929, "y2": 92, "confidence": 1.0}, "box3d": {"alpha": 1.62554, "orientation": 1.58979, "location": [-8.76483, -115.069, 245.087], "dimension": [1.68732, 1.92351, 4.95318]}}, {"id": 227586, "category": "Car", "manualShape": false, "manualAttributes": false, "attributes": {"occluded": 0, "truncated": 0, "ignore": false}, "box2d": {"x1": 929, "y1": 99, "x2": 939, "y2": 106, "confidence": 1.0}, "box3d": {"alpha": 1.43703, "orientation": 1.41002, "location": [-5.71596, -96.0555, 211.568], "dimension": [1.3941, 2.00371, 5.0106]}}, {"id": 231426, "category": "Car", "manualShape": false, "manualAttributes": false, "attributes": {"occluded": 0, "truncated": 0, "ignore": false}, "box2d": {"x1": 939, "y1": 84, "x2": 946, "y2": 92, "confidence": 1.0}, "box3d": {"alpha": 1.61291, "orientation": 1.59505, "location": [-4.36092, -114.471, 244.099], "dimension": [1.95105, 2.10791, 5.10333]}}, {"id": 234498, "category": "Car", "manualShape": false, "manualAttributes": false, "attributes": {"occluded": 0, "truncated": 0, "ignore": false}, "box2d": {"x1": 918, "y1": 88, "x2": 926, "y2": 95, "confidence": 1.0}, "box3d": {"alpha": 1.63505, "orientation": 1.596, "location": [-9.13881, -108.809, 233.927], "dimension": [1.87449, 2.08947, 4.82045]}}, {"id": 236802, "category": "Car", "manualShape": false, "manualAttributes": false, "attributes": {"occluded": 0, "truncated": 0, "ignore": false}, "box2d": {"x1": 934, "y1": 88, "x2": 943, "y2": 96, "confidence": 1.0}, "box3d": {"alpha": 1.7508, "orientation": 1.72878, "location": [-5.15241, -108.789, 233.918], "dimension": [1.88416, 2.01051, 5.55837]}}, {"id": 241154, "category": "Car", "manualShape": false, "manualAttributes": false, "attributes": {"occluded": 0, "truncated": 0, "ignore": false}, "box2d": {"x1": 977, "y1": 53, "x2": 980, "y2": 55, "confidence": 1.0}, "box3d": {"alpha": -1.54434, "orientation": -1.52489, "location": [7.72503, -201.499, 397.113], "dimension": [1.4331, 1.92351, 5.14386]}}, {"id": 251394, "category": "Car", "manualShape": false, "manualAttributes": false, "attributes": {"occluded": 0, "truncated": 0, "ignore": false}, "box2d": {"x1": 926, "y1": 78, "x2": 932, "y2": 82, "confidence": 1.0}, "box3d": {"alpha": 1.63738, "orientation": 1.60574, "location": [-8.65984, -131.167, 273.549], "dimension": [1.49636, 2.00041, 4.91436]}}, {"id": 251906, "category": "Car", "manualShape": false, "manualAttributes": false, "attributes": {"occluded": 0, "truncated": 0, "ignore": false}, "box2d": {"x1": 980, "y1": 44, "x2": 983, "y2": 47, "confidence": 1.0}, "box3d": {"alpha": -1.55211, "orientation": -1.52908, "location": [10.4829, -234.719, 455.064], "dimension": [1.46187, 2.18793, 5.21102]}}, {"id": 255490, "category": "Car", "manualShape": false, "manualAttributes": false, "attributes": {"occluded": 0, "truncated": 0, "ignore": false}, "box2d": {"x1": 987, "y1": 57, "x2": 1000, "y2": 62, "confidence": 1.0}, "box3d": {"alpha": -3.16951, "orientation": -3.13445, "location": [12.6731, -180.745, 361.344], "dimension": [1.88416, 2.01051, 5.55837]}}, {"id": 257026, "category": "Car", "manualShape": false, "manualAttributes": false, "attributes": {"occluded": 0, "truncated": 0, "ignore": false}, "box2d": {"x1": 900, "y1": 72, "x2": 913, "y2": 76, "confidence": 1.0}, "box3d": {"alpha": 3.02915, "orientation": 2.97295, "location": [-16.3115, -140.504, 289.924], "dimension": [1.46187, 2.18793, 5.21102]}}, {"id": 259330, "category": "Car", "manualShape": false, "manualAttributes": false, "attributes": {"occluded": 0, "truncated": 0, "ignore": false}, "box2d": {"x1": 989, "y1": 49, "x2": 992, "y2": 51, "confidence": 1.0}, "box3d": {"alpha": -1.54231, "orientation": -1.50963, "location": [13.7897, -215.57, 421.816], "dimension": [1.46187, 2.18793, 5.21102]}}, {"id": 260098, "category": "Car", "manualShape": false, "manualAttributes": false, "attributes": {"occluded": 0, "truncated": 0, "ignore": false}, "box2d": {"x1": 946, "y1": 76, "x2": 951, "y2": 80, "confidence": 1.0}, "box3d": {"alpha": 1.58382, "orientation": 1.57214, "location": [-3.29436, -135.869, 281.955], "dimension": [1.68732, 1.92351, 4.95318]}}, {"id": 260610, "category": "Car", "manualShape": false, "manualAttributes": false, "attributes": {"occluded": 0, "truncated": 0, "ignore": false}, "box2d": {"x1": 948, "y1": 65, "x2": 952, "y2": 68, "confidence": 1.0}, "box3d": {"alpha": 1.57039, "orientation": 1.56035, "location": [-3.27989, -161.099, 326.553], "dimension": [1.3941, 2.00371, 5.0106]}}]}